fancy_abak/__init__.py
fancy_abak/abak.py
fancy_abak/abak_config/__init__.py
fancy_abak/abak_config/config.py
fancy_abak/abak_config/remove.py
fancy_abak/abak_config/set.py
fancy_abak/abak_config/show.py
fancy_abak/abak_context/__init__.py
fancy_abak/abak_context/abak_context.py
fancy_abak/abak_shared_functions/__init__.py
fancy_abak/abak_shared_functions/abak_configuration_functions.py
fancy_abak/abak_shared_functions/bsgenerator.py
fancy_abak/abak_shared_functions/exceptions.py
fancy_abak/abak_shared_functions/option_check.py
fancy_abak/abak_shared_functions/requests_functions.py
fancy_abak/client/__init__.py
fancy_abak/client/clients.py
fancy_abak/do.py
fancy_abak/project/__init__.py
fancy_abak/project/projects.py
fancy_abak/timesheets/__init__.py
fancy_abak/timesheets/timesheets.py
fancy_abak-2.0.0.dist-info/LICENSE
fancy_abak-2.0.0.dist-info/METADATA
fancy_abak-2.0.0.dist-info/WHEEL
fancy_abak-2.0.0.dist-info/entry_points.txt
fancy_abak-2.0.0.dist-info/RECORD
