Metadata-Version: 2.1
Name: fancy-abak
Version: 2.0.0
Summary: Fancy Abak CLI
Home-page: https://abak.fancywhale.ca
License: MIT
Author: Gui Martins
Author-email: gmartins@fancywhale.ca
Requires-Python: >=3.11,<4.0
Classifier: License :: OSI Approved :: MIT License
Classifier: Programming Language :: Python :: 3
Classifier: Programming Language :: Python :: 3.11
Classifier: Programming Language :: Python :: 3.12
Requires-Dist: click (>=8.1.7,<9.0.0)
Requires-Dist: keyring (>=24.2.0,<25.0.0)
Requires-Dist: pyfzf (>=0.3.1,<0.4.0)
Requires-Dist: pyyaml (>=6.0.1,<7.0.0)
Requires-Dist: requests (>=2.31.0,<3.0.0)
Requires-Dist: tabulate (>=0.9.0,<0.10.0)
Requires-Dist: zipp (>=3.17.0,<4.0.0)
